gptauthor/console.py
gptauthor/library/classes.py
gptauthor/library/consts.py
gptauthor/library/engine.py
gptauthor/library/env.py
gptauthor/library/llm.py
gptauthor/library/log.py
gptauthor/library/prompts.py
gptauthor/library/utils.py
gptauthor/prompts-echoes-of-atlantis.yaml
gptauthor/prompts-gptauthor-meta.yaml
gptauthor/prompts-gptauthor-usage.yaml
gptauthor/prompts-openai-drama.yaml
gptauthor/prompts-scifi-simulation.yaml
gptauthor-1.0.4.dist-info/LICENSE
gptauthor-1.0.4.dist-info/METADATA
gptauthor-1.0.4.dist-info/WHEEL
gptauthor-1.0.4.dist-info/entry_points.txt
gptauthor-1.0.4.dist-info/RECORD
