Metadata-Version: 2.1
Name: gptauthor
Version: 1.0.4
Summary: GPTAuthor is a tool for writing long form stories using AI
Home-page: https://github.com/dylanhogg/gptauthor
License: MIT
Keywords: GPTAuthor
Author: Dylan Hogg
Author-email: dylanhogg@gmail.com
Requires-Python: >=3.10,<4.0
Classifier: Development Status :: 5 - Production/Stable
Classifier: License :: OSI Approved :: MIT License
Classifier: Programming Language :: Python :: 3
Classifier: Programming Language :: Python :: 3.10
Classifier: Programming Language :: Python :: 3.11
Classifier: Programming Language :: Python :: 3.12
Classifier: Topic :: Games/Entertainment
Classifier: Topic :: Scientific/Engineering :: Artificial Intelligence
Requires-Dist: beautifulsoup4 (>=4.13.3,<5.0.0)
Requires-Dist: click (>=8.1.8,<9.0.0)
Requires-Dist: httpx (>=0.25.0,<0.26.0)
Requires-Dist: joblib (>=1.4.2,<2.0.0)
Requires-Dist: loguru (>=0.7.2,<0.8.0)
Requires-Dist: markdown (>=3.7,<4.0)
Requires-Dist: matplotlib (>=3.10.1,<4.0.0)
Requires-Dist: networkx (>=3.4.2,<4.0.0)
Requires-Dist: omegaconf (>=2.3.0,<3.0.0)
Requires-Dist: openai (>=1.66.3,<2.0.0)
Requires-Dist: python-dotenv (>=1.0.1,<2.0.0)
Requires-Dist: pyvis (>=0.3.2,<0.4.0)
Requires-Dist: rich (>=13.9.4,<14.0.0)
Requires-Dist: tenacity (>=9.0.0,<10.0.0)
Requires-Dist: tqdm (>=4.67.1,<5.0.0)
Requires-Dist: typer (>=0.9.0,<0.10.0)
Project-URL: Repository, https://github.com/dylanhogg/gptauthor
